ovos_skill_local_media/LICENSE
ovos_skill_local_media/MANIFEST.in
ovos_skill_local_media/README.md
ovos_skill_local_media/__init__.py
ovos_skill_local_media/notify-requirements.txt
ovos_skill_local_media/requirements.txt
ovos_skill_local_media/version.py
ovos_skill_local_media/gui/ovos-file-browser.svg
ovos_skill_local_media/gui/qt5/Browser.qml
ovos_skill_local_media/gui/qt5/BrowserView.qml
ovos_skill_local_media/gui/qt5/ControllerArea.qml
ovos_skill_local_media/gui/qt5/FileItemDelegate.qml
ovos_skill_local_media/gui/qt5/ImageViewer.qml
ovos_skill_local_media/gui/qt5/KdeConnectDevices.qml
ovos_skill_local_media/gui/qt5/MenuButton.qml
ovos_skill_local_media/gui/qt5/PlacesView.qml
ovos_skill_local_media/gui/qt5/ShareButton.qml
ovos_skill_local_media/gui/qt5/images/generic-audio-bg.jpg
ovos_skill_local_media/gui/qt5/images/share-bluetooth.svg
ovos_skill_local_media/gui/qt5/images/share-kdeconnect.png
ovos_skill_local_media/gui/qt5/sounds/clicked.wav
ovos_skill_local_media/locale/da-dk/open.file.browser.intent
ovos_skill_local_media/locale/da-dk/skill.json
ovos_skill_local_media/locale/da-dk/intents/open.file.browser.intent
ovos_skill_local_media/locale/de-de/open.file.browser.intent
ovos_skill_local_media/locale/de-de/skill.json
ovos_skill_local_media/locale/de-de/intents/open.file.browser.intent
ovos_skill_local_media/locale/en-us/local_media.voc
ovos_skill_local_media/locale/en-us/open.file.browser.intent
ovos_skill_local_media/locale/en-us/skill.json
ovos_skill_local_media/locale/en-us/intents/open.file.browser.intent
ovos_skill_local_media/locale/es-es/intents/open.file.browser.intent
ovos_skill_local_media/locale/eu/open.file.browser.intent
ovos_skill_local_media/locale/eu/intents/open.file.browser.intent
ovos_skill_local_media/locale/fr-fr/intents/open.file.browser.intent
ovos_skill_local_media/locale/gl-es/open.file.browser.intent
ovos_skill_local_media/locale/gl-es/intents/open.file.browser.intent
ovos_skill_local_media/locale/it-it/skill.json
ovos_skill_local_media/ovos_skill_local_media.egg-info/PKG-INFO
ovos_skill_local_media/ovos_skill_local_media.egg-info/SOURCES.txt
ovos_skill_local_media/ovos_skill_local_media.egg-info/dependency_links.txt
ovos_skill_local_media/ovos_skill_local_media.egg-info/entry_points.txt
ovos_skill_local_media/ovos_skill_local_media.egg-info/requires.txt
ovos_skill_local_media/ovos_skill_local_media.egg-info/top_level.txt
ovos_skill_local_media-0.2.12.dist-info/LICENSE
ovos_skill_local_media-0.2.12.dist-info/METADATA
ovos_skill_local_media-0.2.12.dist-info/WHEEL
ovos_skill_local_media-0.2.12.dist-info/entry_points.txt
ovos_skill_local_media-0.2.12.dist-info/top_level.txt
ovos_skill_local_media-0.2.12.dist-info/RECORD
