Metadata-Version: 2.1
Name: ovos-skill-local-media
Version: 0.2.12
Summary: OVOS file browser OCP skill plugin
Home-page: https://github.com/OpenVoiceOS/ovos-skill-local-media
Author: Aix
Author-email: aix.m@outlook.com
License: Apache-2.0
Keywords: ovos file browser skill plugin
License-File: LICENSE
Requires-Dist: ovos-utils>=0.1.0
Requires-Dist: ovos-bus-client<2.0.0,>=0.0.9
Requires-Dist: ovos-workshop<8.0.0,>=2.4.0
Provides-Extra: notify
Requires-Dist: pyudev; extra == "notify"
